{
  "generated_at_utc": "2026-03-26T00:04:45Z",
  "source": "yfinance",
  "interval": "1d",
  "lookback": "400d",
  "trading_days": 252,
  "count": 31,
  "data": [
    {
      "symbol": "^DJI",
      "name": "Dow Jones Industrial Average (DJIA)",
      "price": 46429.488281,
      "close_d1": 46124.058594,
      "change_pts": 305.429688,
      "change_pct": 0.00662192,
      "daily_7d": [
        {
          "date": "2026-03-17",
          "close": 46993.261719
        },
        {
          "date": "2026-03-18",
          "close": 46225.148438
        },
        {
          "date": "2026-03-19",
          "close": 46021.429688
        },
        {
          "date": "2026-03-20",
          "close": 45577.46875
        },
        {
          "date": "2026-03-23",
          "close": 46208.46875
        },
        {
          "date": "2026-03-24",
          "close": 46124.058594
        },
        {
          "date": "2026-03-25",
          "close": 46429.488281
        }
      ],
      "vol_annual": 0.151709,
      "vol_semiannual": 0.12554265,
      "vol_quarterly": 0.13431297,
      "vol_monthly": 0.13455706,
      "vol_weekly": 0.16148389
    },
    {
      "symbol": "^NYA",
      "name": "NYSE Composite Index",
      "price": 22127.621094,
      "close_d1": 21971.300781,
      "change_pts": 156.320312,
      "change_pct": 0.00711475,
      "daily_7d": [
        {
          "date": "2026-03-17",
          "close": 22315.539062
        },
        {
          "date": "2026-03-18",
          "close": 21996.599609
        },
        {
          "date": "2026-03-19",
          "close": 21941.029297
        },
        {
          "date": "2026-03-20",
          "close": 21616.730469
        },
        {
          "date": "2026-03-23",
          "close": 21910.769531
        },
        {
          "date": "2026-03-24",
          "close": 21971.300781
        },
        {
          "date": "2026-03-25",
          "close": 22127.621094
        }
      ],
      "vol_annual": 0.14128876,
      "vol_semiannual": 0.11789418,
      "vol_quarterly": 0.12609483,
      "vol_monthly": 0.14525153,
      "vol_weekly": 0.19316952
    },
    {
      "symbol": "^IXIC",
      "name": "Nasdaq Composite Index",
      "price": 21929.826172,
      "close_d1": 21761.890625,
      "change_pts": 167.935547,
      "change_pct": 0.00771696,
      "daily_7d": [
        {
          "date": "2026-03-17",
          "close": 22479.529297
        },
        {
          "date": "2026-03-18",
          "close": 22152.419922
        },
        {
          "date": "2026-03-19",
          "close": 22090.689453
        },
        {
          "date": "2026-03-20",
          "close": 21647.609375
        },
        {
          "date": "2026-03-23",
          "close": 21946.759766
        },
        {
          "date": "2026-03-24",
          "close": 21761.890625
        },
        {
          "date": "2026-03-25",
          "close": 21929.826172
        }
      ],
      "vol_annual": 0.21813339,
      "vol_semiannual": 0.17415369,
      "vol_quarterly": 0.15959721,
      "vol_monthly": 0.17623862,
      "vol_weekly": 0.24527306
    },
    {
      "symbol": "^NDX",
      "name": "Nasdaq 100 (NDX)",
      "price": 24162.976562,
      "close_d1": 24002.449219,
      "change_pts": 160.527344,
      "change_pct": 0.00668796,
      "daily_7d": [
        {
          "date": "2026-03-17",
          "close": 24780.419922
        },
        {
          "date": "2026-03-18",
          "close": 24425.089844
        },
        {
          "date": "2026-03-19",
          "close": 24355.279297
        },
        {
          "date": "2026-03-20",
          "close": 23898.150391
        },
        {
          "date": "2026-03-23",
          "close": 24188.589844
        },
        {
          "date": "2026-03-24",
          "close": 24002.449219
        },
        {
          "date": "2026-03-25",
          "close": 24162.976562
        }
      ],
      "vol_annual": 0.21387982,
      "vol_semiannual": 0.17439961,
      "vol_quarterly": 0.16084224,
      "vol_monthly": 0.16737376,
      "vol_weekly": 0.22324917
    },
    {
      "symbol": "^GSPTSE",
      "name": "S&P/TSX Composite Index",
      "price": 32382.599609,
      "close_d1": 31941.599609,
      "change_pts": 441.0,
      "change_pct": 0.01380645,
      "daily_7d": [
        {
          "date": "2026-03-17",
          "close": 32929.101562
        },
        {
          "date": "2026-03-18",
          "close": 32312.699219
        },
        {
          "date": "2026-03-19",
          "close": 31855.0
        },
        {
          "date": "2026-03-20",
          "close": 31317.400391
        },
        {
          "date": "2026-03-23",
          "close": 31883.800781
        },
        {
          "date": "2026-03-24",
          "close": 31941.599609
        },
        {
          "date": "2026-03-25",
          "close": 32382.599609
        }
      ],
      "vol_annual": 0.13779874,
      "vol_semiannual": 0.15225744,
      "vol_quarterly": 0.17248011,
      "vol_monthly": 0.18420349,
      "vol_weekly": 0.24844373
    },
    {
      "symbol": "TX60.TS",
      "name": "S&P/TSX 60 Index",
      "price": 1887.540039,
      "close_d1": null,
      "change_pts": null,
      "change_pct": null,
      "daily_7d": [
        {
          "date": "2026-03-25",
          "close": 1887.540039
        }
      ],
      "vol_annual": null,
      "vol_semiannual": null,
      "vol_quarterly": null,
      "vol_monthly": null,
      "vol_weekly": null
    },
    {
      "symbol": "^FTSE",
      "name": "FTSE 100",
      "price": 10106.839844,
      "close_d1": 9965.200195,
      "change_pts": 141.639648,
      "change_pct": 0.01421343,
      "daily_7d": [
        {
          "date": "2026-03-17",
          "close": 10403.599609
        },
        {
          "date": "2026-03-18",
          "close": 10305.299805
        },
        {
          "date": "2026-03-19",
          "close": 10063.5
        },
        {
          "date": "2026-03-20",
          "close": 9918.299805
        },
        {
          "date": "2026-03-23",
          "close": 9894.200195
        },
        {
          "date": "2026-03-24",
          "close": 9965.200195
        },
        {
          "date": "2026-03-25",
          "close": 10106.839844
        }
      ],
      "vol_annual": 0.11782904,
      "vol_semiannual": 0.11577058,
      "vol_quarterly": 0.13772095,
      "vol_monthly": 0.19029077,
      "vol_weekly": 0.19717602
    },
    {
      "symbol": "^FTMC",
      "name": "FTSE 250",
      "price": 21475.449219,
      "close_d1": 21135.800781,
      "change_pts": 339.648438,
      "change_pct": 0.01606982,
      "daily_7d": [
        {
          "date": "2026-03-17",
          "close": 22186.599609
        },
        {
          "date": "2026-03-18",
          "close": 22080.800781
        },
        {
          "date": "2026-03-19",
          "close": 21560.0
        },
        {
          "date": "2026-03-20",
          "close": 21342.0
        },
        {
          "date": "2026-03-23",
          "close": 21246.699219
        },
        {
          "date": "2026-03-24",
          "close": 21135.800781
        },
        {
          "date": "2026-03-25",
          "close": 21475.449219
        }
      ],
      "vol_annual": 0.13077017,
      "vol_semiannual": 0.11996506,
      "vol_quarterly": 0.14158087,
      "vol_monthly": 0.19332517,
      "vol_weekly": 0.18352917
    },
    {
      "symbol": "^FCHI",
      "name": "CAC 40 (France)",
      "price": 7846.549805,
      "close_d1": 7743.919922,
      "change_pts": 102.629883,
      "change_pct": 0.01325296,
      "daily_7d": [
        {
          "date": "2026-03-17",
          "close": 7974.490234
        },
        {
          "date": "2026-03-18",
          "close": 7969.879883
        },
        {
          "date": "2026-03-19",
          "close": 7807.870117
        },
        {
          "date": "2026-03-20",
          "close": 7665.620117
        },
        {
          "date": "2026-03-23",
          "close": 7726.200195
        },
        {
          "date": "2026-03-24",
          "close": 7743.919922
        },
        {
          "date": "2026-03-25",
          "close": 7846.549805
        }
      ],
      "vol_annual": 0.15123539,
      "vol_semiannual": 0.13214791,
      "vol_quarterly": 0.14909363,
      "vol_monthly": 0.21030401,
      "vol_weekly": 0.21929877
    },
    {
      "symbol": "^AEX",
      "name": "AEX (Netherlands)",
      "price": 983.130005,
      "close_d1": 974.219971,
      "change_pts": 8.910034,
      "change_pct": 0.00914581,
      "daily_7d": [
        {
          "date": "2026-03-17",
          "close": 1012.809998
        },
        {
          "date": "2026-03-18",
          "close": 999.97998
        },
        {
          "date": "2026-03-19",
          "close": 977.630005
        },
        {
          "date": "2026-03-20",
          "close": 961.619995
        },
        {
          "date": "2026-03-23",
          "close": 966.719971
        },
        {
          "date": "2026-03-24",
          "close": 974.219971
        },
        {
          "date": "2026-03-25",
          "close": 983.130005
        }
      ],
      "vol_annual": 0.1409481,
      "vol_semiannual": 0.13880982,
      "vol_quarterly": 0.16253082,
      "vol_monthly": 0.18839027,
      "vol_weekly": 0.1912351
    },
    {
      "symbol": "^BFX",
      "name": "BEL 20 (Belgium)",
      "price": 5052.970215,
      "close_d1": 4944.990234,
      "change_pts": 107.97998,
      "change_pct": 0.02183624,
      "daily_7d": [
        {
          "date": "2026-03-17",
          "close": 5167.0
        },
        {
          "date": "2026-03-18",
          "close": 5129.080078
        },
        {
          "date": "2026-03-19",
          "close": 5004.77002
        },
        {
          "date": "2026-03-20",
          "close": 4916.790039
        },
        {
          "date": "2026-03-23",
          "close": 4940.02002
        },
        {
          "date": "2026-03-24",
          "close": 4944.990234
        },
        {
          "date": "2026-03-25",
          "close": 5052.970215
        }
      ],
      "vol_annual": 0.14046265,
      "vol_semiannual": 0.13110589,
      "vol_quarterly": 0.16256653,
      "vol_monthly": 0.22253711,
      "vol_weekly": 0.25620256
    },
    {
      "symbol": "^GDAXI",
      "name": "DAX 40 (Germany)",
      "price": 22957.080078,
      "close_d1": 22636.910156,
      "change_pts": 320.169922,
      "change_pct": 0.01414371,
      "daily_7d": [
        {
          "date": "2026-03-17",
          "close": 23730.919922
        },
        {
          "date": "2026-03-18",
          "close": 23502.25
        },
        {
          "date": "2026-03-19",
          "close": 22839.560547
        },
        {
          "date": "2026-03-20",
          "close": 22380.189453
        },
        {
          "date": "2026-03-23",
          "close": 22653.859375
        },
        {
          "date": "2026-03-24",
          "close": 22636.910156
        },
        {
          "date": "2026-03-25",
          "close": 22957.080078
        }
      ],
      "vol_annual": 0.1672282,
      "vol_semiannual": 0.15579494,
      "vol_quarterly": 0.18032981,
      "vol_monthly": 0.25060513,
      "vol_weekly": 0.25129367
    },
    {
      "symbol": "^MDAXI",
      "name": "MDAX (Germany Mid Caps)",
      "price": 28821.320312,
      "close_d1": 28125.109375,
      "change_pts": 696.210938,
      "change_pct": 0.02475407,
      "daily_7d": [
        {
          "date": "2026-03-17",
          "close": 29481.75
        },
        {
          "date": "2026-03-18",
          "close": 29519.419922
        },
        {
          "date": "2026-03-19",
          "close": 28423.080078
        },
        {
          "date": "2026-03-20",
          "close": 27796.279297
        },
        {
          "date": "2026-03-23",
          "close": 28229.359375
        },
        {
          "date": "2026-03-24",
          "close": 28125.109375
        },
        {
          "date": "2026-03-25",
          "close": 28821.320312
        }
      ],
      "vol_annual": 0.18682382,
      "vol_semiannual": 0.18383798,
      "vol_quarterly": 0.21473193,
      "vol_monthly": 0.30486279,
      "vol_weekly": 0.33039124
    },
    {
      "symbol": "^SSMI",
      "name": "SMI - Swiss Market Index",
      "price": 12718.360352,
      "close_d1": 12515.94043,
      "change_pts": 202.419922,
      "change_pct": 0.01617297,
      "daily_7d": [
        {
          "date": "2026-03-17",
          "close": 12962.410156
        },
        {
          "date": "2026-03-18",
          "close": 12765.480469
        },
        {
          "date": "2026-03-19",
          "close": 12459.540039
        },
        {
          "date": "2026-03-20",
          "close": 12320.990234
        },
        {
          "date": "2026-03-23",
          "close": 12389.679688
        },
        {
          "date": "2026-03-24",
          "close": 12515.94043
        },
        {
          "date": "2026-03-25",
          "close": 12718.360352
        }
      ],
      "vol_annual": 0.13966593,
      "vol_semiannual": 0.12335903,
      "vol_quarterly": 0.14546365,
      "vol_monthly": 0.19789126,
      "vol_weekly": 0.18568711
    },
    {
      "symbol": "^SSHI",
      "name": "SPI - Swiss Performance Index",
      "price": 17742.640625,
      "close_d1": 17471.080078,
      "change_pts": 271.560547,
      "change_pct": 0.01554343,
      "daily_7d": [
        {
          "date": "2026-03-17",
          "close": 18041.640625
        },
        {
          "date": "2026-03-18",
          "close": 17804.220703
        },
        {
          "date": "2026-03-19",
          "close": 17379.490234
        },
        {
          "date": "2026-03-20",
          "close": 17202.240234
        },
        {
          "date": "2026-03-23",
          "close": 17311.060547
        },
        {
          "date": "2026-03-24",
          "close": 17471.080078
        },
        {
          "date": "2026-03-25",
          "close": 17742.640625
        }
      ],
      "vol_annual": 0.13180921,
      "vol_semiannual": 0.11578724,
      "vol_quarterly": 0.13699512,
      "vol_monthly": 0.18924355,
      "vol_weekly": 0.17401634
    },
    {
      "symbol": "^BSESN",
      "name": "SENSEX (India)",
      "price": 75273.453125,
      "close_d1": 74068.453125,
      "change_pts": 1205.0,
      "change_pct": 0.01626873,
      "daily_7d": [
        {
          "date": "2026-03-17",
          "close": 76070.84375
        },
        {
          "date": "2026-03-18",
          "close": 76704.132812
        },
        {
          "date": "2026-03-19",
          "close": 74207.242188
        },
        {
          "date": "2026-03-20",
          "close": 74532.960938
        },
        {
          "date": "2026-03-23",
          "close": 72696.390625
        },
        {
          "date": "2026-03-24",
          "close": 74068.453125
        },
        {
          "date": "2026-03-25",
          "close": 75273.453125
        }
      ],
      "vol_annual": 0.12507743,
      "vol_semiannual": 0.13348113,
      "vol_quarterly": 0.17040509,
      "vol_monthly": 0.24675552,
      "vol_weekly": 0.31760068
    },
    {
      "symbol": "^NSEI",
      "name": "NIFTY 50 (India)",
      "price": 23306.449219,
      "close_d1": 22912.400391,
      "change_pts": 394.048828,
      "change_pct": 0.01719806,
      "daily_7d": [
        {
          "date": "2026-03-17",
          "close": 23581.150391
        },
        {
          "date": "2026-03-18",
          "close": 23777.800781
        },
        {
          "date": "2026-03-19",
          "close": 23002.150391
        },
        {
          "date": "2026-03-20",
          "close": 23114.5
        },
        {
          "date": "2026-03-23",
          "close": 22512.650391
        },
        {
          "date": "2026-03-24",
          "close": 22912.400391
        },
        {
          "date": "2026-03-25",
          "close": 23306.449219
        }
      ],
      "vol_annual": 0.12603826,
      "vol_semiannual": 0.13499285,
      "vol_quarterly": 0.17254243,
      "vol_monthly": 0.24863999,
      "vol_weekly": 0.32753907
    },
    {
      "symbol": "^BVSP",
      "name": "Ibovespa (IBOV)",
      "price": 185424.28125,
      "close_d1": 182509.0,
      "change_pts": 2915.28125,
      "change_pct": 0.01597336,
      "daily_7d": [
        {
          "date": "2026-03-17",
          "close": 180410.0
        },
        {
          "date": "2026-03-18",
          "close": 179640.0
        },
        {
          "date": "2026-03-19",
          "close": 180271.0
        },
        {
          "date": "2026-03-20",
          "close": 176219.0
        },
        {
          "date": "2026-03-23",
          "close": 181932.0
        },
        {
          "date": "2026-03-24",
          "close": 182509.0
        },
        {
          "date": "2026-03-25",
          "close": 185424.28125
        }
      ],
      "vol_annual": 0.16419787,
      "vol_semiannual": 0.18930414,
      "vol_quarterly": 0.21928073,
      "vol_monthly": 0.26078099,
      "vol_weekly": 0.36630064
    },
    {
      "symbol": "^IBX50",
      "name": "IBrX 50",
      "price": 31352.949219,
      "close_d1": 30863.259766,
      "change_pts": 489.689453,
      "change_pct": 0.01586642,
      "daily_7d": [
        {
          "date": "2026-03-17",
          "close": 30473.439453
        },
        {
          "date": "2026-03-18",
          "close": 30365.970703
        },
        {
          "date": "2026-03-19",
          "close": 30476.949219
        },
        {
          "date": "2026-03-20",
          "close": 29811.089844
        },
        {
          "date": "2026-03-23",
          "close": 30750.220703
        },
        {
          "date": "2026-03-24",
          "close": 30863.259766
        },
        {
          "date": "2026-03-25",
          "close": 31352.949219
        }
      ],
      "vol_annual": 0.16304801,
      "vol_semiannual": 0.18790626,
      "vol_quarterly": 0.2177898,
      "vol_monthly": 0.25702349,
      "vol_weekly": 0.35620797
    },
    {
      "symbol": "BRAX11.SA",
      "name": "iShares IBrX-Índice Brasil (IBrX-100) ETF (proxy do IBrX 100)",
      "price": 155.240005,
      "close_d1": 152.520004,
      "change_pts": 2.720001,
      "change_pct": 0.01783373,
      "daily_7d": [
        {
          "date": "2026-03-17",
          "close": 151.050003
        },
        {
          "date": "2026-03-18",
          "close": 150.440002
        },
        {
          "date": "2026-03-19",
          "close": 150.940002
        },
        {
          "date": "2026-03-20",
          "close": 147.360001
        },
        {
          "date": "2026-03-23",
          "close": 152.070007
        },
        {
          "date": "2026-03-24",
          "close": 152.520004
        },
        {
          "date": "2026-03-25",
          "close": 155.240005
        }
      ],
      "vol_annual": 0.16252173,
      "vol_semiannual": 0.19367483,
      "vol_quarterly": 0.21856282,
      "vol_monthly": 0.25911795,
      "vol_weekly": 0.37677572
    },
    {
      "symbol": "^N225",
      "name": "Nikkei 225",
      "price": 53749.62,
      "close_d1": 51515.488281,
      "change_pts": 2234.131719,
      "change_pct": 0.04336816,
      "daily_7d": [
        {
          "date": "2026-03-13",
          "close": 53819.609375
        },
        {
          "date": "2026-03-16",
          "close": 53751.148438
        },
        {
          "date": "2026-03-17",
          "close": 53700.390625
        },
        {
          "date": "2026-03-18",
          "close": 55239.398438
        },
        {
          "date": "2026-03-19",
          "close": 53372.53125
        },
        {
          "date": "2026-03-23",
          "close": 51515.488281
        },
        {
          "date": "2026-03-24",
          "close": 52252.28125
        }
      ],
      "vol_annual": 0.27516499,
      "vol_semiannual": 0.2639585,
      "vol_quarterly": 0.28865009,
      "vol_monthly": 0.37305033,
      "vol_weekly": null
    },
    {
      "symbol": "1306.T",
      "name": "NEXT FUNDS TOPIX ETF (proxy do TOPIX)",
      "price": 3836.0,
      "close_d1": 3743.0,
      "change_pts": 93.0,
      "change_pct": 0.02484638,
      "daily_7d": [
        {
          "date": "2026-03-16",
          "close": 3790.0
        },
        {
          "date": "2026-03-17",
          "close": 3809.0
        },
        {
          "date": "2026-03-18",
          "close": 3907.0
        },
        {
          "date": "2026-03-19",
          "close": 3791.0
        },
        {
          "date": "2026-03-23",
          "close": 3659.0
        },
        {
          "date": "2026-03-24",
          "close": 3743.0
        },
        {
          "date": "2026-03-25",
          "close": 3836.0
        }
      ],
      "vol_annual": 0.23588188,
      "vol_semiannual": 0.2158262,
      "vol_quarterly": 0.25609765,
      "vol_monthly": 0.34875964,
      "vol_weekly": 0.02071215
    },
    {
      "symbol": "^KS11",
      "name": "KOSPI (South Korea)",
      "price": 5642.21,
      "close_d1": 5405.75,
      "change_pts": 236.46,
      "change_pct": 0.04374231,
      "daily_7d": [
        {
          "date": "2026-03-16",
          "close": 5549.850098
        },
        {
          "date": "2026-03-17",
          "close": 5640.47998
        },
        {
          "date": "2026-03-18",
          "close": 5925.029785
        },
        {
          "date": "2026-03-19",
          "close": 5763.220215
        },
        {
          "date": "2026-03-20",
          "close": 5781.200195
        },
        {
          "date": "2026-03-23",
          "close": 5405.75
        },
        {
          "date": "2026-03-24",
          "close": 5553.919922
        }
      ],
      "vol_annual": 0.28900047,
      "vol_semiannual": 0.42057499,
      "vol_quarterly": 0.53281187,
      "vol_monthly": 0.81508423,
      "vol_weekly": 0.7771725
    },
    {
      "symbol": "^KQ11",
      "name": "KOSDAQ (South Korea)",
      "price": 1159.55,
      "close_d1": 1096.890015,
      "change_pts": 62.659985,
      "change_pct": 0.05712513,
      "daily_7d": [
        {
          "date": "2026-03-16",
          "close": 1138.290039
        },
        {
          "date": "2026-03-17",
          "close": 1136.939941
        },
        {
          "date": "2026-03-18",
          "close": 1164.380005
        },
        {
          "date": "2026-03-19",
          "close": 1143.47998
        },
        {
          "date": "2026-03-20",
          "close": 1161.52002
        },
        {
          "date": "2026-03-23",
          "close": 1096.890015
        },
        {
          "date": "2026-03-24",
          "close": 1121.439941
        }
      ],
      "vol_annual": 0.32133682,
      "vol_semiannual": 0.43506073,
      "vol_quarterly": 0.58021442,
      "vol_monthly": 0.88756118,
      "vol_weekly": 0.69976973
    },
    {
      "symbol": "000001.SS",
      "name": "SSE Composite Index (Shanghai)",
      "price": 3931.837402,
      "close_d1": 3881.280029,
      "change_pts": 50.557373,
      "change_pct": 0.01302595,
      "daily_7d": [
        {
          "date": "2026-03-17",
          "close": 4049.906982
        },
        {
          "date": "2026-03-18",
          "close": 4062.983887
        },
        {
          "date": "2026-03-19",
          "close": 4006.552002
        },
        {
          "date": "2026-03-20",
          "close": 3957.052979
        },
        {
          "date": "2026-03-23",
          "close": 3813.282959
        },
        {
          "date": "2026-03-24",
          "close": 3881.280029
        },
        {
          "date": "2026-03-25",
          "close": 3931.837402
        }
      ],
      "vol_annual": 0.16137503,
      "vol_semiannual": 0.13549885,
      "vol_quarterly": 0.15366064,
      "vol_monthly": 0.18945019,
      "vol_weekly": 0.40112642
    },
    {
      "symbol": "000300.SS",
      "name": "CSI 300 (Shanghai + Shenzhen)",
      "price": 4537.46582,
      "close_d1": 4474.720215,
      "change_pts": 62.745605,
      "change_pct": 0.01402224,
      "daily_7d": [
        {
          "date": "2026-03-17",
          "close": 4637.439941
        },
        {
          "date": "2026-03-18",
          "close": 4658.330078
        },
        {
          "date": "2026-03-19",
          "close": 4583.25
        },
        {
          "date": "2026-03-20",
          "close": 4567.02002
        },
        {
          "date": "2026-03-23",
          "close": 4418.0
        },
        {
          "date": "2026-03-24",
          "close": 4474.720215
        },
        {
          "date": "2026-03-25",
          "close": 4537.46582
        }
      ],
      "vol_annual": 0.17979125,
      "vol_semiannual": 0.14953933,
      "vol_quarterly": 0.14851204,
      "vol_monthly": 0.1838151,
      "vol_weekly": 0.34833875
    },
    {
      "symbol": "399001.SZ",
      "name": "SZSE Component Index (Shenzhen)",
      "price": 13801.000977,
      "close_d1": 13536.55957,
      "change_pts": 264.441406,
      "change_pct": 0.01953535,
      "daily_7d": [
        {
          "date": "2026-03-17",
          "close": 14039.730469
        },
        {
          "date": "2026-03-18",
          "close": 14187.799805
        },
        {
          "date": "2026-03-19",
          "close": 13901.570312
        },
        {
          "date": "2026-03-20",
          "close": 13866.200195
        },
        {
          "date": "2026-03-23",
          "close": 13345.509766
        },
        {
          "date": "2026-03-24",
          "close": 13536.55957
        },
        {
          "date": "2026-03-25",
          "close": 13801.000977
        }
      ],
      "vol_annual": 0.23568192,
      "vol_semiannual": 0.20776397,
      "vol_quarterly": 0.20341229,
      "vol_monthly": 0.24813137,
      "vol_weekly": 0.41340599
    },
    {
      "symbol": "399006.SZ",
      "name": "ChiNext Index (Shenzhen)",
      "price": 3316.971436,
      "close_d1": null,
      "change_pts": null,
      "change_pct": null,
      "daily_7d": [
        {
          "date": "2026-03-25",
          "close": 3316.971436
        }
      ],
      "vol_annual": null,
      "vol_semiannual": null,
      "vol_quarterly": null,
      "vol_monthly": null,
      "vol_weekly": null
    },
    {
      "symbol": "^HSI",
      "name": "Hang Seng Index (HK50)",
      "price": 25335.949219,
      "close_d1": 25063.710938,
      "change_pts": 272.238281,
      "change_pct": 0.01086185,
      "daily_7d": [
        {
          "date": "2026-03-17",
          "close": 25868.539062
        },
        {
          "date": "2026-03-18",
          "close": 26025.419922
        },
        {
          "date": "2026-03-19",
          "close": 25500.580078
        },
        {
          "date": "2026-03-20",
          "close": 25277.320312
        },
        {
          "date": "2026-03-23",
          "close": 24382.470703
        },
        {
          "date": "2026-03-24",
          "close": 25063.710938
        },
        {
          "date": "2026-03-25",
          "close": 25335.949219
        }
      ],
      "vol_annual": 0.22514932,
      "vol_semiannual": 0.19939462,
      "vol_quarterly": 0.21489814,
      "vol_monthly": 0.26178699,
      "vol_weekly": 0.43396975
    },
    {
      "symbol": "^AXJO",
      "name": "S&P/ASX 200",
      "price": 8524.799805,
      "close_d1": 8379.400391,
      "change_pts": 145.399414,
      "change_pct": 0.01735201,
      "daily_7d": [
        {
          "date": "2026-03-17",
          "close": 8614.299805
        },
        {
          "date": "2026-03-18",
          "close": 8640.599609
        },
        {
          "date": "2026-03-19",
          "close": 8497.799805
        },
        {
          "date": "2026-03-20",
          "close": 8428.400391
        },
        {
          "date": "2026-03-23",
          "close": 8365.900391
        },
        {
          "date": "2026-03-24",
          "close": 8379.400391
        },
        {
          "date": "2026-03-26",
          "close": 8524.799805
        }
      ],
      "vol_annual": 0.12280592,
      "vol_semiannual": 0.12641803,
      "vol_quarterly": 0.14403893,
      "vol_monthly": 0.16145322,
      "vol_weekly": 0.08667316
    },
    {
      "symbol": "^STI",
      "name": "Straits Times Index (Singapore)",
      "price": 4904.540039,
      "close_d1": 4862.430176,
      "change_pts": 42.109863,
      "change_pct": 0.00866025,
      "daily_7d": [
        {
          "date": "2026-03-17",
          "close": 4935.970215
        },
        {
          "date": "2026-03-18",
          "close": 5002.169922
        },
        {
          "date": "2026-03-19",
          "close": 4967.609863
        },
        {
          "date": "2026-03-20",
          "close": 4948.870117
        },
        {
          "date": "2026-03-23",
          "close": 4841.299805
        },
        {
          "date": "2026-03-24",
          "close": 4862.430176
        },
        {
          "date": "2026-03-25",
          "close": 4904.540039
        }
      ],
      "vol_annual": 0.12750646,
      "vol_semiannual": 0.11606744,
      "vol_quarterly": 0.13983648,
      "vol_monthly": 0.19768313,
      "vol_weekly": 0.21489066
    }
  ]
}