{
  "generated_at_utc": "2026-07-14T10:16:26Z",
  "source": "yfinance",
  "interval": "1d",
  "lookback": "400d",
  "trading_days": 252,
  "count": 31,
  "data": [
    {
      "symbol": "^DJI",
      "name": "Dow Jones Industrial Average (DJIA)",
      "price": 52498.640625,
      "close_d1": 52637.011719,
      "change_pts": -138.371094,
      "change_pct": -0.00262878,
      "daily_7d": [
        {
          "date": "2026-07-02",
          "close": 52900.070312
        },
        {
          "date": "2026-07-06",
          "close": 53055.910156
        },
        {
          "date": "2026-07-07",
          "close": 52925.148438
        },
        {
          "date": "2026-07-08",
          "close": 52348.390625
        },
        {
          "date": "2026-07-09",
          "close": 52487.410156
        },
        {
          "date": "2026-07-10",
          "close": 52637.011719
        },
        {
          "date": "2026-07-13",
          "close": 52498.640625
        }
      ],
      "vol_annual": 0.15577349,
      "vol_semiannual": 0.14105883,
      "vol_quarterly": 0.12610797,
      "vol_monthly": 0.08842088,
      "vol_weekly": 0.10278097
    },
    {
      "symbol": "^NYA",
      "name": "NYSE Composite Index",
      "price": 23896.050781,
      "close_d1": 23925.070312,
      "change_pts": -29.019531,
      "change_pct": -0.00121293,
      "daily_7d": [
        {
          "date": "2026-07-02",
          "close": 23957.080078
        },
        {
          "date": "2026-07-06",
          "close": 24075.119141
        },
        {
          "date": "2026-07-07",
          "close": 24016.960938
        },
        {
          "date": "2026-07-08",
          "close": 23790.599609
        },
        {
          "date": "2026-07-09",
          "close": 23876.839844
        },
        {
          "date": "2026-07-10",
          "close": 23925.070312
        },
        {
          "date": "2026-07-13",
          "close": 23896.050781
        }
      ],
      "vol_annual": 0.14563625,
      "vol_semiannual": 0.1273971,
      "vol_quarterly": 0.1102273,
      "vol_monthly": 0.08314552,
      "vol_weekly": 0.09253901
    },
    {
      "symbol": "^IXIC",
      "name": "Nasdaq Composite Index",
      "price": 25873.179688,
      "close_d1": 26281.609375,
      "change_pts": -408.429688,
      "change_pct": -0.01554051,
      "daily_7d": [
        {
          "date": "2026-07-02",
          "close": 25832.669922
        },
        {
          "date": "2026-07-06",
          "close": 26121.160156
        },
        {
          "date": "2026-07-07",
          "close": 25818.689453
        },
        {
          "date": "2026-07-08",
          "close": 25870.650391
        },
        {
          "date": "2026-07-09",
          "close": 26206.890625
        },
        {
          "date": "2026-07-10",
          "close": 26281.609375
        },
        {
          "date": "2026-07-13",
          "close": 25873.179688
        }
      ],
      "vol_annual": 0.22751895,
      "vol_semiannual": 0.20512568,
      "vol_quarterly": 0.20716956,
      "vol_monthly": 0.20436257,
      "vol_weekly": 0.18852237
    },
    {
      "symbol": "^NDX",
      "name": "Nasdaq 100 (NDX)",
      "price": 29264.099609,
      "close_d1": 29825.109375,
      "change_pts": -561.009766,
      "change_pct": -0.01880998,
      "daily_7d": [
        {
          "date": "2026-07-02",
          "close": 29329.210938
        },
        {
          "date": "2026-07-06",
          "close": 29697.869141
        },
        {
          "date": "2026-07-07",
          "close": 29173.019531
        },
        {
          "date": "2026-07-08",
          "close": 29252.560547
        },
        {
          "date": "2026-07-09",
          "close": 29727.099609
        },
        {
          "date": "2026-07-10",
          "close": 29825.109375
        },
        {
          "date": "2026-07-13",
          "close": 29264.099609
        }
      ],
      "vol_annual": 0.22806071,
      "vol_semiannual": 0.22145772,
      "vol_quarterly": 0.24438214,
      "vol_monthly": 0.27307233,
      "vol_weekly": 0.23101957
    },
    {
      "symbol": "^GSPTSE",
      "name": "S&P/TSX Composite Index",
      "price": null,
      "close_d1": null,
      "change_pts": null,
      "change_pct": null,
      "daily_7d": [],
      "vol_annual": null,
      "vol_semiannual": null,
      "vol_quarterly": null,
      "vol_monthly": null,
      "vol_weekly": null
    },
    {
      "symbol": "TX60.TS",
      "name": "S&P/TSX 60 Index",
      "price": 2084.469971,
      "close_d1": null,
      "change_pts": null,
      "change_pct": null,
      "daily_7d": [
        {
          "date": "2026-07-13",
          "close": 2084.469971
        }
      ],
      "vol_annual": null,
      "vol_semiannual": null,
      "vol_quarterly": null,
      "vol_monthly": null,
      "vol_weekly": null
    },
    {
      "symbol": "^FTSE",
      "name": "FTSE 100",
      "price": 10452.650391,
      "close_d1": 10498.299805,
      "change_pts": -45.649414,
      "change_pct": -0.00434827,
      "daily_7d": [
        {
          "date": "2026-07-06",
          "close": 10651.799805
        },
        {
          "date": "2026-07-07",
          "close": 10665.900391
        },
        {
          "date": "2026-07-08",
          "close": 10489.0
        },
        {
          "date": "2026-07-09",
          "close": 10472.5
        },
        {
          "date": "2026-07-10",
          "close": 10497.299805
        },
        {
          "date": "2026-07-13",
          "close": 10498.299805
        },
        {
          "date": "2026-07-14",
          "close": 10452.650391
        }
      ],
      "vol_annual": 0.12518161,
      "vol_semiannual": 0.13915831,
      "vol_quarterly": 0.12415401,
      "vol_monthly": 0.10482587,
      "vol_weekly": 0.11911432
    },
    {
      "symbol": "^FTMC",
      "name": "FTSE 250",
      "price": 23229.140625,
      "close_d1": 23396.599609,
      "change_pts": -167.458984,
      "change_pct": -0.00715741,
      "daily_7d": [
        {
          "date": "2026-07-06",
          "close": 23504.199219
        },
        {
          "date": "2026-07-07",
          "close": 23378.800781
        },
        {
          "date": "2026-07-08",
          "close": 23017.599609
        },
        {
          "date": "2026-07-09",
          "close": 23240.599609
        },
        {
          "date": "2026-07-10",
          "close": 23371.400391
        },
        {
          "date": "2026-07-13",
          "close": 23396.599609
        },
        {
          "date": "2026-07-14",
          "close": 23229.140625
        }
      ],
      "vol_annual": 0.13898094,
      "vol_semiannual": 0.15270292,
      "vol_quarterly": 0.12496381,
      "vol_monthly": 0.10940643,
      "vol_weekly": 0.16099341
    },
    {
      "symbol": "^FCHI",
      "name": "CAC 40 (France)",
      "price": 8305.849609,
      "close_d1": 8364.650391,
      "change_pts": -58.800781,
      "change_pct": -0.00702968,
      "daily_7d": [
        {
          "date": "2026-07-06",
          "close": 8479.870117
        },
        {
          "date": "2026-07-07",
          "close": 8436.240234
        },
        {
          "date": "2026-07-08",
          "close": 8252.660156
        },
        {
          "date": "2026-07-09",
          "close": 8326.620117
        },
        {
          "date": "2026-07-10",
          "close": 8338.969727
        },
        {
          "date": "2026-07-13",
          "close": 8364.650391
        },
        {
          "date": "2026-07-14",
          "close": 8305.849609
        }
      ],
      "vol_annual": 0.15634589,
      "vol_semiannual": 0.16388263,
      "vol_quarterly": 0.15030115,
      "vol_monthly": 0.12726294,
      "vol_weekly": 0.19058398
    },
    {
      "symbol": "^AEX",
      "name": "AEX (Netherlands)",
      "price": 1082.829956,
      "close_d1": 1085.400024,
      "change_pts": -2.570068,
      "change_pct": -0.00236785,
      "daily_7d": [
        {
          "date": "2026-07-06",
          "close": 1082.410034
        },
        {
          "date": "2026-07-07",
          "close": 1079.0
        },
        {
          "date": "2026-07-08",
          "close": 1076.150024
        },
        {
          "date": "2026-07-09",
          "close": 1083.319946
        },
        {
          "date": "2026-07-10",
          "close": 1084.22998
        },
        {
          "date": "2026-07-13",
          "close": 1085.400024
        },
        {
          "date": "2026-07-14",
          "close": 1082.829956
        }
      ],
      "vol_annual": 0.14359776,
      "vol_semiannual": 0.14391777,
      "vol_quarterly": 0.12639385,
      "vol_monthly": 0.10735968,
      "vol_weekly": 0.0594332
    },
    {
      "symbol": "^BFX",
      "name": "BEL 20 (Belgium)",
      "price": 5578.919922,
      "close_d1": 5604.450195,
      "change_pts": -25.530273,
      "change_pct": -0.00455536,
      "daily_7d": [
        {
          "date": "2026-07-06",
          "close": 5732.450195
        },
        {
          "date": "2026-07-07",
          "close": 5724.430176
        },
        {
          "date": "2026-07-08",
          "close": 5630.299805
        },
        {
          "date": "2026-07-09",
          "close": 5647.959961
        },
        {
          "date": "2026-07-10",
          "close": 5594.080078
        },
        {
          "date": "2026-07-13",
          "close": 5604.450195
        },
        {
          "date": "2026-07-14",
          "close": 5578.919922
        }
      ],
      "vol_annual": 0.14946594,
      "vol_semiannual": 0.16434239,
      "vol_quarterly": 0.14385992,
      "vol_monthly": 0.13126429,
      "vol_weekly": 0.13000698
    },
    {
      "symbol": "^GDAXI",
      "name": "DAX 40 (Germany)",
      "price": 24999.429688,
      "close_d1": 25114.25,
      "change_pts": -114.820312,
      "change_pct": -0.00457192,
      "daily_7d": [
        {
          "date": "2026-07-06",
          "close": 25817.890625
        },
        {
          "date": "2026-07-07",
          "close": 25465.25
        },
        {
          "date": "2026-07-08",
          "close": 24897.449219
        },
        {
          "date": "2026-07-09",
          "close": 25118.269531
        },
        {
          "date": "2026-07-10",
          "close": 25067.089844
        },
        {
          "date": "2026-07-13",
          "close": 25114.25
        },
        {
          "date": "2026-07-14",
          "close": 24999.429688
        }
      ],
      "vol_annual": 0.17861731,
      "vol_semiannual": 0.19369525,
      "vol_quarterly": 0.16873908,
      "vol_monthly": 0.15929558,
      "vol_weekly": 0.18563181
    },
    {
      "symbol": "^MDAXI",
      "name": "MDAX (Germany Mid Caps)",
      "price": 31747.220703,
      "close_d1": 31981.810547,
      "change_pts": -234.589844,
      "change_pct": -0.0073351,
      "daily_7d": [
        {
          "date": "2026-07-06",
          "close": 33291.238281
        },
        {
          "date": "2026-07-07",
          "close": 32627.039062
        },
        {
          "date": "2026-07-08",
          "close": 31516.349609
        },
        {
          "date": "2026-07-09",
          "close": 31837.349609
        },
        {
          "date": "2026-07-10",
          "close": 31919.449219
        },
        {
          "date": "2026-07-13",
          "close": 31981.810547
        },
        {
          "date": "2026-07-14",
          "close": 31747.220703
        }
      ],
      "vol_annual": 0.20365505,
      "vol_semiannual": 0.22978727,
      "vol_quarterly": 0.20213074,
      "vol_monthly": 0.19121998,
      "vol_weekly": 0.27694747
    },
    {
      "symbol": "^SSMI",
      "name": "SMI - Swiss Market Index",
      "price": 14171.019531,
      "close_d1": 14266.179688,
      "change_pts": -95.160156,
      "change_pct": -0.00667033,
      "daily_7d": [
        {
          "date": "2026-07-06",
          "close": 14302.259766
        },
        {
          "date": "2026-07-07",
          "close": 14360.450195
        },
        {
          "date": "2026-07-08",
          "close": 14174.349609
        },
        {
          "date": "2026-07-09",
          "close": 14215.299805
        },
        {
          "date": "2026-07-10",
          "close": 14235.089844
        },
        {
          "date": "2026-07-13",
          "close": 14266.179688
        },
        {
          "date": "2026-07-14",
          "close": 14171.019531
        }
      ],
      "vol_annual": 0.14351667,
      "vol_semiannual": 0.14213789,
      "vol_quarterly": 0.12499271,
      "vol_monthly": 0.11294156,
      "vol_weekly": 0.11074904
    },
    {
      "symbol": "^SSHI",
      "name": "SPI - Swiss Performance Index",
      "price": 19935.810547,
      "close_d1": 20064.960938,
      "change_pts": -129.150391,
      "change_pct": -0.00643661,
      "daily_7d": [
        {
          "date": "2026-07-06",
          "close": 20166.929688
        },
        {
          "date": "2026-07-07",
          "close": 20202.919922
        },
        {
          "date": "2026-07-08",
          "close": 19931.890625
        },
        {
          "date": "2026-07-09",
          "close": 19998.189453
        },
        {
          "date": "2026-07-10",
          "close": 20023.150391
        },
        {
          "date": "2026-07-13",
          "close": 20064.960938
        },
        {
          "date": "2026-07-14",
          "close": 19935.810547
        }
      ],
      "vol_annual": 0.13542038,
      "vol_semiannual": 0.1346276,
      "vol_quarterly": 0.11692995,
      "vol_monthly": 0.10664677,
      "vol_weekly": 0.11381597
    },
    {
      "symbol": "^BSESN",
      "name": "SENSEX (India)",
      "price": 77054.9375,
      "close_d1": 77616.398438,
      "change_pts": -561.460938,
      "change_pct": -0.00723379,
      "daily_7d": [
        {
          "date": "2026-07-06",
          "close": 78285.070312
        },
        {
          "date": "2026-07-07",
          "close": 78180.71875
        },
        {
          "date": "2026-07-08",
          "close": 76503.601562
        },
        {
          "date": "2026-07-09",
          "close": 76741.820312
        },
        {
          "date": "2026-07-10",
          "close": 77569.390625
        },
        {
          "date": "2026-07-13",
          "close": 77616.398438
        },
        {
          "date": "2026-07-14",
          "close": 77054.9375
        }
      ],
      "vol_annual": 0.13269853,
      "vol_semiannual": 0.1725963,
      "vol_quarterly": 0.13444641,
      "vol_monthly": 0.12943091,
      "vol_weekly": 0.1953862
    },
    {
      "symbol": "^NSEI",
      "name": "NIFTY 50 (India)",
      "price": 24052.050781,
      "close_d1": 24211.0,
      "change_pts": -158.949219,
      "change_pct": -0.00656517,
      "daily_7d": [
        {
          "date": "2026-07-06",
          "close": 24430.349609
        },
        {
          "date": "2026-07-07",
          "close": 24398.699219
        },
        {
          "date": "2026-07-08",
          "close": 23882.050781
        },
        {
          "date": "2026-07-09",
          "close": 23962.800781
        },
        {
          "date": "2026-07-10",
          "close": 24206.900391
        },
        {
          "date": "2026-07-13",
          "close": 24211.0
        },
        {
          "date": "2026-07-14",
          "close": 24052.050781
        }
      ],
      "vol_annual": 0.13149109,
      "vol_semiannual": 0.1681262,
      "vol_quarterly": 0.12556307,
      "vol_monthly": 0.12312552,
      "vol_weekly": 0.19027064
    },
    {
      "symbol": "^BVSP",
      "name": "Ibovespa (IBOV)",
      "price": 175739.0,
      "close_d1": 177866.0,
      "change_pts": -2127.0,
      "change_pct": -0.01195844,
      "daily_7d": [
        {
          "date": "2026-07-03",
          "close": 174266.0
        },
        {
          "date": "2026-07-06",
          "close": 172448.0
        },
        {
          "date": "2026-07-07",
          "close": 172021.0
        },
        {
          "date": "2026-07-08",
          "close": 170654.0
        },
        {
          "date": "2026-07-09",
          "close": 172742.0
        },
        {
          "date": "2026-07-10",
          "close": 177866.0
        },
        {
          "date": "2026-07-13",
          "close": 175739.0
        }
      ],
      "vol_annual": 0.17047798,
      "vol_semiannual": 0.19869261,
      "vol_quarterly": 0.1621177,
      "vol_monthly": 0.15488972,
      "vol_weekly": 0.30348096
    },
    {
      "symbol": "^IBX50",
      "name": "IBrX 50",
      "price": 29542.369141,
      "close_d1": 29865.5,
      "change_pts": -323.130859,
      "change_pct": -0.01081954,
      "daily_7d": [
        {
          "date": "2026-07-03",
          "close": 29346.089844
        },
        {
          "date": "2026-07-06",
          "close": 29033.210938
        },
        {
          "date": "2026-07-07",
          "close": 28958.339844
        },
        {
          "date": "2026-07-08",
          "close": 28722.119141
        },
        {
          "date": "2026-07-09",
          "close": 29043.0
        },
        {
          "date": "2026-07-10",
          "close": 29865.5
        },
        {
          "date": "2026-07-13",
          "close": 29542.369141
        }
      ],
      "vol_annual": 0.16859972,
      "vol_semiannual": 0.19516997,
      "vol_quarterly": 0.15639782,
      "vol_monthly": 0.14976378,
      "vol_weekly": 0.28824018
    },
    {
      "symbol": "BRAX11.SA",
      "name": "iShares IBrX-Índice Brasil (IBrX-100) ETF (proxy do IBrX 100)",
      "price": 147.100006,
      "close_d1": 148.759995,
      "change_pts": -1.659988,
      "change_pct": -0.01115884,
      "daily_7d": [
        {
          "date": "2026-07-03",
          "close": 145.800003
        },
        {
          "date": "2026-07-06",
          "close": 144.440002
        },
        {
          "date": "2026-07-07",
          "close": 144.089996
        },
        {
          "date": "2026-07-08",
          "close": 142.929993
        },
        {
          "date": "2026-07-09",
          "close": 144.600006
        },
        {
          "date": "2026-07-10",
          "close": 148.759995
        },
        {
          "date": "2026-07-13",
          "close": 147.100006
        }
      ],
      "vol_annual": 0.16918849,
      "vol_semiannual": 0.19570507,
      "vol_quarterly": 0.15768032,
      "vol_monthly": 0.15046036,
      "vol_weekly": 0.29325543
    },
    {
      "symbol": "^N225",
      "name": "Nikkei 225",
      "price": 67743.5,
      "close_d1": 67242.726562,
      "change_pts": 500.773438,
      "change_pct": 0.00744725,
      "daily_7d": [
        {
          "date": "2026-07-06",
          "close": 69737.6875
        },
        {
          "date": "2026-07-07",
          "close": 68256.960938
        },
        {
          "date": "2026-07-08",
          "close": 66819.046875
        },
        {
          "date": "2026-07-09",
          "close": 67743.851562
        },
        {
          "date": "2026-07-10",
          "close": 68557.726562
        },
        {
          "date": "2026-07-13",
          "close": 67242.726562
        },
        {
          "date": "2026-07-14",
          "close": 67743.5
        }
      ],
      "vol_annual": 0.25658077,
      "vol_semiannual": 0.31260823,
      "vol_quarterly": 0.29811406,
      "vol_monthly": 0.32489937,
      "vol_weekly": 0.27536858
    },
    {
      "symbol": "1306.T",
      "name": "NEXT FUNDS TOPIX ETF (proxy do TOPIX)",
      "price": 421.299988,
      "close_d1": 417.799988,
      "change_pts": 3.5,
      "change_pct": 0.00837721,
      "daily_7d": [
        {
          "date": "2026-07-06",
          "close": 435.399994
        },
        {
          "date": "2026-07-07",
          "close": 431.799988
        },
        {
          "date": "2026-07-08",
          "close": 426.5
        },
        {
          "date": "2026-07-09",
          "close": 419.100006
        },
        {
          "date": "2026-07-10",
          "close": 422.100006
        },
        {
          "date": "2026-07-13",
          "close": 417.799988
        },
        {
          "date": "2026-07-14",
          "close": 421.299988
        }
      ],
      "vol_annual": 2.71035502,
      "vol_semiannual": 4.93462669,
      "vol_quarterly": 0.17720022,
      "vol_monthly": 0.18277025,
      "vol_weekly": 0.18832992
    },
    {
      "symbol": "^KS11",
      "name": "KOSPI (South Korea)",
      "price": 6856.830078,
      "close_d1": 6806.930176,
      "change_pts": 49.899902,
      "change_pct": 0.00733075,
      "daily_7d": [
        {
          "date": "2026-07-06",
          "close": 8051.330078
        },
        {
          "date": "2026-07-07",
          "close": 7656.310059
        },
        {
          "date": "2026-07-08",
          "close": 7246.790039
        },
        {
          "date": "2026-07-09",
          "close": 7291.910156
        },
        {
          "date": "2026-07-10",
          "close": 7475.939941
        },
        {
          "date": "2026-07-13",
          "close": 6806.930176
        },
        {
          "date": "2026-07-14",
          "close": 6856.830078
        }
      ],
      "vol_annual": 0.37714032,
      "vol_semiannual": 0.61270497,
      "vol_quarterly": 0.64353829,
      "vol_monthly": 0.73512915,
      "vol_weekly": 0.79733725
    },
    {
      "symbol": "^KQ11",
      "name": "KOSDAQ (South Korea)",
      "price": 783.97998,
      "close_d1": 799.359985,
      "change_pts": -15.380005,
      "change_pct": -0.0192404,
      "daily_7d": [
        {
          "date": "2026-07-06",
          "close": 847.070007
        },
        {
          "date": "2026-07-07",
          "close": 831.22998
        },
        {
          "date": "2026-07-08",
          "close": 785.0
        },
        {
          "date": "2026-07-09",
          "close": 794.0
        },
        {
          "date": "2026-07-10",
          "close": 837.429993
        },
        {
          "date": "2026-07-13",
          "close": 799.359985
        },
        {
          "date": "2026-07-14",
          "close": 783.97998
        }
      ],
      "vol_annual": 0.36729984,
      "vol_semiannual": 0.58315459,
      "vol_quarterly": 0.54143298,
      "vol_monthly": 0.60885396,
      "vol_weekly": 0.71424534
    },
    {
      "symbol": "000001.SS",
      "name": "SSE Composite Index (Shanghai)",
      "price": 3967.126221,
      "close_d1": 3913.793945,
      "change_pts": 53.332275,
      "change_pct": 0.01362675,
      "daily_7d": [
        {
          "date": "2026-07-06",
          "close": 4041.238037
        },
        {
          "date": "2026-07-07",
          "close": 3990.235107
        },
        {
          "date": "2026-07-08",
          "close": 3970.879883
        },
        {
          "date": "2026-07-09",
          "close": 4036.587891
        },
        {
          "date": "2026-07-10",
          "close": 3996.162109
        },
        {
          "date": "2026-07-13",
          "close": 3913.793945
        },
        {
          "date": "2026-07-14",
          "close": 3967.126221
        }
      ],
      "vol_annual": 0.12832774,
      "vol_semiannual": 0.15780355,
      "vol_quarterly": 0.15088925,
      "vol_monthly": 0.18356509,
      "vol_weekly": 0.25156515
    },
    {
      "symbol": "000300.SS",
      "name": "CSI 300 (Shanghai + Shenzhen)",
      "price": 4796.501953,
      "close_d1": 4780.790039,
      "change_pts": 15.711914,
      "change_pct": 0.00328647,
      "daily_7d": [
        {
          "date": "2026-07-03",
          "close": 4842.169922
        },
        {
          "date": "2026-07-06",
          "close": 4842.0
        },
        {
          "date": "2026-07-07",
          "close": 4792.259766
        },
        {
          "date": "2026-07-08",
          "close": 4755.529785
        },
        {
          "date": "2026-07-09",
          "close": 4876.310059
        },
        {
          "date": "2026-07-10",
          "close": 4780.790039
        },
        {
          "date": "2026-07-14",
          "close": 4796.501953
        }
      ],
      "vol_annual": 0.15116121,
      "vol_semiannual": 0.18845203,
      "vol_quarterly": 0.20131242,
      "vol_monthly": 0.26226431,
      "vol_weekly": 0.36849562
    },
    {
      "symbol": "399001.SZ",
      "name": "SZSE Component Index (Shenzhen)",
      "price": 14924.868164,
      "close_d1": 14522.849609,
      "change_pts": 402.018555,
      "change_pct": 0.0276818,
      "daily_7d": [
        {
          "date": "2026-07-06",
          "close": 15416.799805
        },
        {
          "date": "2026-07-07",
          "close": 15225.110352
        },
        {
          "date": "2026-07-08",
          "close": 14939.730469
        },
        {
          "date": "2026-07-09",
          "close": 15398.730469
        },
        {
          "date": "2026-07-10",
          "close": 15046.669922
        },
        {
          "date": "2026-07-13",
          "close": 14522.849609
        },
        {
          "date": "2026-07-14",
          "close": 14924.868164
        }
      ],
      "vol_annual": 0.21052128,
      "vol_semiannual": 0.26509208,
      "vol_quarterly": 0.2878914,
      "vol_monthly": 0.35894179,
      "vol_weekly": 0.4847882
    },
    {
      "symbol": "399006.SZ",
      "name": "ChiNext Index (Shenzhen)",
      "price": 3851.137207,
      "close_d1": null,
      "change_pts": null,
      "change_pct": null,
      "daily_7d": [
        {
          "date": "2026-07-14",
          "close": 3851.137207
        }
      ],
      "vol_annual": null,
      "vol_semiannual": null,
      "vol_quarterly": null,
      "vol_monthly": null,
      "vol_weekly": null
    },
    {
      "symbol": "^HSI",
      "name": "Hang Seng Index (HK50)",
      "price": 24340.730469,
      "close_d1": 24213.720703,
      "change_pts": 127.009766,
      "change_pct": 0.00524536,
      "daily_7d": [
        {
          "date": "2026-07-06",
          "close": 23616.320312
        },
        {
          "date": "2026-07-07",
          "close": 23496.890625
        },
        {
          "date": "2026-07-08",
          "close": 24199.460938
        },
        {
          "date": "2026-07-09",
          "close": 24030.179688
        },
        {
          "date": "2026-07-10",
          "close": 24175.119141
        },
        {
          "date": "2026-07-13",
          "close": 24213.720703
        },
        {
          "date": "2026-07-14",
          "close": 24340.730469
        }
      ],
      "vol_annual": 0.19804445,
      "vol_semiannual": 0.20225169,
      "vol_quarterly": 0.18295876,
      "vol_monthly": 0.21503949,
      "vol_weekly": 0.2150984
    },
    {
      "symbol": "^AXJO",
      "name": "S&P/ASX 200",
      "price": 8808.5,
      "close_d1": 8808.5,
      "change_pts": 0.0,
      "change_pct": 0.0,
      "daily_7d": [
        {
          "date": "2026-07-06",
          "close": 8831.0
        },
        {
          "date": "2026-07-07",
          "close": 8803.900391
        },
        {
          "date": "2026-07-08",
          "close": 8785.099609
        },
        {
          "date": "2026-07-09",
          "close": 8762.5
        },
        {
          "date": "2026-07-10",
          "close": 8806.0
        },
        {
          "date": "2026-07-13",
          "close": 8808.5
        },
        {
          "date": "2026-07-14",
          "close": 8808.5
        }
      ],
      "vol_annual": 0.13002921,
      "vol_semiannual": 0.14494928,
      "vol_quarterly": 0.12143325,
      "vol_monthly": 0.08410037,
      "vol_weekly": 0.04746039
    },
    {
      "symbol": "^STI",
      "name": "Straits Times Index (Singapore)",
      "price": 5495.609863,
      "close_d1": 5470.339844,
      "change_pts": 25.27002,
      "change_pct": 0.00461946,
      "daily_7d": [
        {
          "date": "2026-07-06",
          "close": 5259.810059
        },
        {
          "date": "2026-07-07",
          "close": 5342.240234
        },
        {
          "date": "2026-07-08",
          "close": 5369.569824
        },
        {
          "date": "2026-07-09",
          "close": 5433.879883
        },
        {
          "date": "2026-07-10",
          "close": 5469.290039
        },
        {
          "date": "2026-07-13",
          "close": 5470.339844
        },
        {
          "date": "2026-07-14",
          "close": 5495.609863
        }
      ],
      "vol_annual": 0.13092991,
      "vol_semiannual": 0.12860085,
      "vol_quarterly": 0.11430407,
      "vol_monthly": 0.09309199,
      "vol_weekly": 0.06689033
    }
  ]
}